{"type":"FeatureCollection", "features": [
{"type":"Feature","geometry":{"type":"Point","coordinates":[-95.9865047,36.1619158]},"properties":{"location_id":727,"year":"1920","title":"Vernon AME Church","addresses":[{"id":727,"building_id":727,"is_primary":true,"house_number":"311","prefix":"N","name":"Greenwood","suffix":"Ave","city":"Tulsa","postal_code":null,"created_at":"2025-06-06T22:57:44.473Z","updated_at":"2025-06-17T22:34:20.620Z","year":null,"searchable_text":"311 N Greenwood Ave Tulsa"}],"audios":[],"stories":[],"videos":[],"photos":[],"documents":[],"description":"<i data-poi></i>","rich_description":{"id":27,"name":"description","body":"<pre>&lt;i data-poi&gt;&lt;/i&gt;</pre>","record_type":"Building","record_id":727,"created_at":"2025-06-17T22:34:20.617Z","updated_at":"2025-06-17T22:34:20.617Z"},"census_records":[],"people":[{"id":8196,"created_at":"2025-06-06T23:22:50.977Z","updated_at":"2025-06-06T23:22:50.977Z","last_name":"Cherry","first_name":"William","middle_name":"M","sex":"Male","race":"Black","name_prefix":null,"name_suffix":null,"searchable_name":"William M Cherry","birth_year":1870,"is_birth_year_estimated":true,"pob":"Texas","is_pob_estimated":true,"notes":null,"description":null,"sortable_name":"Cherry, William, M","death_year":null},{"id":8197,"created_at":"2025-06-06T23:22:51.050Z","updated_at":"2025-06-06T23:22:51.050Z","last_name":"Cherry","first_name":"Bessie","middle_name":null,"sex":"Female","race":"Black","name_prefix":null,"name_suffix":null,"searchable_name":"Bessie Cherry","birth_year":1878,"is_birth_year_estimated":true,"pob":"Texas","is_pob_estimated":true,"notes":null,"description":null,"sortable_name":"Cherry, Bessie, ","death_year":null},{"id":8198,"created_at":"2025-06-06T23:22:51.118Z","updated_at":"2025-06-06T23:22:51.118Z","last_name":"Cherry","first_name":"Cleopatra","middle_name":null,"sex":"Female","race":"Black","name_prefix":null,"name_suffix":null,"searchable_name":"Cleopatra Cherry","birth_year":1917,"is_birth_year_estimated":true,"pob":"Texas","is_pob_estimated":true,"notes":null,"description":null,"sortable_name":"Cherry, Cleopatra, ","death_year":null}]}},
{"type":"Feature","geometry":{"type":"Point","coordinates":[-95.9862529,36.1604779]},"properties":{"location_id":770,"year":"1920","title":"119 N Greenwood Street","addresses":[{"id":770,"building_id":770,"is_primary":true,"house_number":"119","prefix":"N","name":"Greenwood Street","suffix":null,"city":"Tulsa","postal_code":null,"created_at":"2025-06-06T22:57:51.611Z","updated_at":"2025-06-06T22:57:51.611Z","year":null,"searchable_text":"119 N Greenwood Street  Tulsa"}],"audios":[],"stories":[{"record":{"id":6,"created_by_id":2,"reviewed_by_id":null,"reviewed_at":null,"weight":0,"source":null,"notes":"","date_type":null,"date_text":null,"date_start":null,"date_end":null,"created_at":"2025-06-17T22:01:00.408Z","updated_at":"2025-06-17T22:01:00.415Z","searchable_text":null},"sources":{"id":19,"name":"sources","body":"<div>The Oklahoma Eagle</div>","record_type":"Narrative","record_id":6,"created_at":"2025-06-17T22:01:00.415Z","updated_at":"2025-06-17T22:01:00.415Z"},"story":{"id":18,"name":"story","body":"<div>O.W. Gurley also owned a two-story building at 119 N. Greenwood. It housed Carter’s Barbershop, Hardy Rooms, a pool hall, and cigar store.</div>","record_type":"Narrative","record_id":6,"created_at":"2025-06-17T22:01:00.413Z","updated_at":"2025-06-17T22:01:00.413Z"}}],"videos":[],"photos":[],"documents":[],"description":"<i data-poi></i>","rich_description":{"id":20,"name":"description","body":"<pre>&lt;i data-poi&gt;&lt;/i&gt;</pre>","record_type":"Building","record_id":770,"created_at":"2025-06-17T22:02:14.794Z","updated_at":"2025-06-17T22:02:14.794Z"},"census_records":[],"people":[{"id":8366,"created_at":"2025-06-06T23:23:03.996Z","updated_at":"2025-06-06T23:23:03.996Z","last_name":"Newkirk","first_name":"Amos","middle_name":"S","sex":"Male","race":"Black","name_prefix":null,"name_suffix":null,"searchable_name":"Amos S Newkirk","birth_year":1880,"is_birth_year_estimated":true,"pob":"North Carolina","is_pob_estimated":true,"notes":null,"description":null,"sortable_name":"Newkirk, Amos, S","death_year":null},{"id":8367,"created_at":"2025-06-06T23:23:04.072Z","updated_at":"2025-06-06T23:23:04.072Z","last_name":"Newkirk","first_name":"Rebecca","middle_name":null,"sex":"Female","race":"Black","name_prefix":null,"name_suffix":null,"searchable_name":"Rebecca Newkirk","birth_year":1892,"is_birth_year_estimated":true,"pob":"Louisiana","is_pob_estimated":true,"notes":null,"description":null,"sortable_name":"Newkirk, Rebecca, ","death_year":null},{"id":8368,"created_at":"2025-06-06T23:23:04.151Z","updated_at":"2025-06-06T23:23:04.151Z","last_name":"Newkirk","first_name":"Henry","middle_name":null,"sex":"Male","race":"Black","name_prefix":null,"name_suffix":null,"searchable_name":"Henry Newkirk","birth_year":1909,"is_birth_year_estimated":true,"pob":"Oklahoma","is_pob_estimated":true,"notes":null,"description":null,"sortable_name":"Newkirk, Henry, ","death_year":null},{"id":8369,"created_at":"2025-06-06T23:23:04.226Z","updated_at":"2025-06-06T23:23:04.226Z","last_name":"Newkirk","first_name":"Eldridge","middle_name":null,"sex":"Male","race":"Black","name_prefix":null,"name_suffix":null,"searchable_name":"Eldridge Newkirk","birth_year":1914,"is_birth_year_estimated":true,"pob":"Oklahoma","is_pob_estimated":true,"notes":null,"description":null,"sortable_name":"Newkirk, Eldridge, ","death_year":null},{"id":8370,"created_at":"2025-06-06T23:23:04.300Z","updated_at":"2025-06-06T23:23:04.300Z","last_name":"Newkirk","first_name":"Almadge","middle_name":null,"sex":"Male","race":"Black","name_prefix":null,"name_suffix":null,"searchable_name":"Almadge Newkirk","birth_year":1914,"is_birth_year_estimated":true,"pob":"Oklahoma","is_pob_estimated":true,"notes":null,"description":null,"sortable_name":"Newkirk, Almadge, ","death_year":null},{"id":8371,"created_at":"2025-06-06T23:23:04.369Z","updated_at":"2025-06-06T23:23:04.369Z","last_name":"Smith","first_name":"S","middle_name":"F","sex":"Male","race":"Black","name_prefix":null,"name_suffix":null,"searchable_name":"S F Smith","birth_year":1885,"is_birth_year_estimated":true,"pob":"Oklahoma","is_pob_estimated":true,"notes":null,"description":null,"sortable_name":"Smith, S, F","death_year":null},{"id":8372,"created_at":"2025-06-06T23:23:04.439Z","updated_at":"2025-06-06T23:23:04.439Z","last_name":"Smith","first_name":"Hattie","middle_name":null,"sex":"Female","race":"Black","name_prefix":null,"name_suffix":null,"searchable_name":"Hattie Smith","birth_year":1880,"is_birth_year_estimated":true,"pob":"Arkansas","is_pob_estimated":true,"notes":null,"description":null,"sortable_name":"Smith, Hattie, ","death_year":null},{"id":8373,"created_at":"2025-06-06T23:23:04.513Z","updated_at":"2025-06-06T23:23:04.513Z","last_name":"Smith","first_name":"Cornell","middle_name":null,"sex":"Male","race":"Black","name_prefix":null,"name_suffix":null,"searchable_name":"Cornell Smith","birth_year":1897,"is_birth_year_estimated":true,"pob":"Oklahoma","is_pob_estimated":true,"notes":null,"description":null,"sortable_name":"Smith, Cornell, ","death_year":null},{"id":9353,"created_at":"2025-06-06T23:24:20.837Z","updated_at":"2025-06-06T23:24:20.837Z","last_name":"Newkirk","first_name":"Madison","middle_name":null,"sex":"Male","race":"Black","name_prefix":null,"name_suffix":null,"searchable_name":"Madison Newkirk","birth_year":1913,"is_birth_year_estimated":true,"pob":"Oklahoma","is_pob_estimated":true,"notes":null,"description":null,"sortable_name":"Newkirk, Madison, ","death_year":null}]}},
{"type":"Feature","geometry":{"type":"Point","coordinates":[-95.9860501,36.1600879]},"properties":{"location_id":766,"year":"1920","title":"103 N. Greenwood Ave.","addresses":[{"id":766,"building_id":766,"is_primary":true,"house_number":"103","prefix":"N","name":"Greenwood","suffix":"Ave","city":"Tulsa","postal_code":null,"created_at":"2025-06-06T22:57:51.004Z","updated_at":"2025-06-17T19:31:44.423Z","year":null,"searchable_text":"103 N Greenwood Ave Tulsa"}],"audios":[],"stories":[{"record":{"id":7,"created_by_id":2,"reviewed_by_id":2,"reviewed_at":"2025-06-17T22:17:22.314Z","weight":0,"source":null,"notes":"","date_type":null,"date_text":"2021","date_start":null,"date_end":null,"created_at":"2025-06-17T22:17:19.652Z","updated_at":"2025-06-17T22:17:22.321Z","searchable_text":null},"sources":{"id":22,"name":"sources","body":"<div>New York Times,&nbsp;</div>","record_type":"Narrative","record_id":7,"created_at":"2025-06-17T22:17:19.661Z","updated_at":"2025-06-17T22:17:19.661Z"},"story":{"id":21,"name":"story","body":"<div><strong>Dr. R.T. Bridgewater</strong> was a physician with a practice in the Woods Building, at 101-105 Greenwood Avenue. He owned 17 rental houses and was also a community leader. The Tulsa Star, a Black-owned newspaper, called his home on the affluent North Detroit Street “palatial.”<br><br>...Several women set up shop as entrepreneurs in the same building. <strong>Mary E. Jones Parrish</strong>, left, was a teacher and journalist who operated a typing school. <strong>Mabel B. Little</strong> ran the Little Rose Beauty Salon.</div>","record_type":"Narrative","record_id":7,"created_at":"2025-06-17T22:17:19.658Z","updated_at":"2025-06-17T22:17:19.658Z"}}],"videos":[],"photos":[],"documents":[],"description":"<i data-poi></i>","rich_description":{"id":4,"name":"description","body":"<pre>&lt;i data-poi&gt;&lt;/i&gt;</pre>","record_type":"Building","record_id":766,"created_at":"2025-06-17T19:27:08.838Z","updated_at":"2025-06-17T19:27:08.838Z"},"census_records":[],"people":[{"id":8353,"created_at":"2025-06-06T23:23:02.971Z","updated_at":"2025-06-11T03:33:09.097Z","last_name":"Little","first_name":"Mabel","middle_name":"B","sex":"F","race":"B","name_prefix":null,"name_suffix":null,"searchable_name":"Mabel B Little","birth_year":1896,"is_birth_year_estimated":true,"pob":"Texas","is_pob_estimated":true,"notes":"","description":"It was Mabel Little’s lifelong dream to graduate from Langston University. Her dream finally came true upon the completion of her autobiography, written in 1990. Langston published the book and awarded Little with an honorary degree. She was 94 years old. She passed away on January 13th, 2001.","sortable_name":"Little, Mabel, B","death_year":null},{"id":8352,"created_at":"2025-06-06T23:23:02.897Z","updated_at":"2025-06-06T23:23:02.897Z","last_name":"Little","first_name":"Pressly","middle_name":null,"sex":"Male","race":"Black","name_prefix":null,"name_suffix":null,"searchable_name":"Pressly Little","birth_year":1894,"is_birth_year_estimated":true,"pob":"Arkansas","is_pob_estimated":true,"notes":null,"description":null,"sortable_name":"Little, Pressly, ","death_year":null},{"id":8354,"created_at":"2025-06-06T23:23:03.046Z","updated_at":"2025-06-06T23:23:03.046Z","last_name":"Anderson","first_name":"Cansada","middle_name":null,"sex":"Female","race":"Black","name_prefix":null,"name_suffix":null,"searchable_name":"Cansada Anderson","birth_year":1872,"is_birth_year_estimated":true,"pob":"Texas","is_pob_estimated":true,"notes":null,"description":null,"sortable_name":"Anderson, Cansada, ","death_year":null},{"id":8355,"created_at":"2025-06-06T23:23:03.133Z","updated_at":"2025-06-06T23:23:03.133Z","last_name":"Roshon","first_name":"Abe","middle_name":"A","sex":"Male","race":"Black","name_prefix":null,"name_suffix":null,"searchable_name":"Abe A Roshon","birth_year":1895,"is_birth_year_estimated":true,"pob":"Louisiana","is_pob_estimated":true,"notes":null,"description":null,"sortable_name":"Roshon, Abe, A","death_year":null},{"id":8356,"created_at":"2025-06-06T23:23:03.211Z","updated_at":"2025-06-06T23:23:03.211Z","last_name":"Flemings","first_name":"Marvin","middle_name":null,"sex":"Male","race":"Black","name_prefix":null,"name_suffix":null,"searchable_name":"Marvin Flemings","birth_year":1898,"is_birth_year_estimated":true,"pob":"Missouri","is_pob_estimated":true,"notes":null,"description":null,"sortable_name":"Flemings, Marvin, ","death_year":null},{"id":8357,"created_at":"2025-06-06T23:23:03.286Z","updated_at":"2025-06-06T23:23:03.286Z","last_name":"Flemings","first_name":"Halyrd","middle_name":null,"sex":"Male","race":"Black","name_prefix":null,"name_suffix":null,"searchable_name":"Halyrd Flemings","birth_year":1900,"is_birth_year_estimated":true,"pob":"Missouri","is_pob_estimated":true,"notes":null,"description":null,"sortable_name":"Flemings, Halyrd, ","death_year":null}]}},
{"type":"Feature","geometry":{"type":"Point","coordinates":[-95.9862778,36.159961]},"properties":{"location_id":781,"year":"1920","title":"Williams Building","addresses":[{"id":781,"building_id":781,"is_primary":true,"house_number":"102","prefix":"N","name":"Greenwood","suffix":"Ave","city":"Tulsa","postal_code":null,"created_at":"2025-06-06T22:57:54.270Z","updated_at":"2025-06-17T19:29:01.882Z","year":null,"searchable_text":"102 N Greenwood Ave Tulsa"}],"audios":[],"stories":[],"videos":[],"photos":[],"documents":[],"description":"<i data-poi></i>","rich_description":{"id":3,"name":"description","body":"<pre>&lt;i data-poi&gt;&lt;/i&gt;</pre>","record_type":"Building","record_id":781,"created_at":"2025-06-16T18:12:33.459Z","updated_at":"2025-06-16T18:12:33.459Z"},"census_records":[],"people":[{"id":8436,"created_at":"2025-06-06T23:23:10.756Z","updated_at":"2025-06-06T23:23:10.756Z","last_name":"Williams","first_name":"John","middle_name":"W","sex":"Male","race":"Black","name_prefix":null,"name_suffix":null,"searchable_name":"John W Williams","birth_year":1882,"is_birth_year_estimated":true,"pob":"Mississippi","is_pob_estimated":true,"notes":null,"description":null,"sortable_name":"Williams, John, W","death_year":null},{"id":8437,"created_at":"2025-06-06T23:23:10.829Z","updated_at":"2025-06-06T23:23:10.829Z","last_name":"Williams","first_name":"Loula","middle_name":"T","sex":"Female","race":"Black","name_prefix":null,"name_suffix":null,"searchable_name":"Loula T Williams","birth_year":1879,"is_birth_year_estimated":true,"pob":"Tennessee","is_pob_estimated":true,"notes":null,"description":null,"sortable_name":"Williams, Loula, T","death_year":null},{"id":8438,"created_at":"2025-06-06T23:23:10.900Z","updated_at":"2025-06-06T23:23:10.900Z","last_name":"Williams","first_name":"Willie","middle_name":null,"sex":"Male","race":"Black","name_prefix":null,"name_suffix":null,"searchable_name":"Willie Williams","birth_year":1906,"is_birth_year_estimated":true,"pob":"Arkansas","is_pob_estimated":true,"notes":null,"description":null,"sortable_name":"Williams, Willie, ","death_year":null},{"id":8441,"created_at":"2025-06-06T23:23:11.117Z","updated_at":"2025-06-06T23:23:11.117Z","last_name":"Montgomery","first_name":"Hosea","middle_name":null,"sex":"Male","race":"Black","name_prefix":null,"name_suffix":null,"searchable_name":"Hosea Montgomery","birth_year":1904,"is_birth_year_estimated":true,"pob":"Alabama","is_pob_estimated":true,"notes":null,"description":null,"sortable_name":"Montgomery, Hosea, ","death_year":null},{"id":8442,"created_at":"2025-06-06T23:23:11.188Z","updated_at":"2025-06-06T23:23:11.188Z","last_name":"Campbell","first_name":"Henry","middle_name":null,"sex":"Male","race":"Black","name_prefix":null,"name_suffix":null,"searchable_name":"Henry Campbell","birth_year":1877,"is_birth_year_estimated":true,"pob":"Arkansas","is_pob_estimated":true,"notes":null,"description":null,"sortable_name":"Campbell, Henry, ","death_year":null},{"id":8443,"created_at":"2025-06-06T23:23:11.285Z","updated_at":"2025-06-06T23:23:11.285Z","last_name":"Robertson","first_name":"Eloise","middle_name":null,"sex":"Female","race":"Black","name_prefix":null,"name_suffix":null,"searchable_name":"Eloise Robertson","birth_year":1912,"is_birth_year_estimated":true,"pob":"Tennessee","is_pob_estimated":true,"notes":null,"description":null,"sortable_name":"Robertson, Eloise, ","death_year":null},{"id":8444,"created_at":"2025-06-06T23:23:11.366Z","updated_at":"2025-06-06T23:23:11.366Z","last_name":"Floyd","first_name":"Elmore","middle_name":null,"sex":"Male","race":"Black","name_prefix":null,"name_suffix":null,"searchable_name":"Elmore Floyd","birth_year":1898,"is_birth_year_estimated":true,"pob":"Georgia","is_pob_estimated":true,"notes":null,"description":null,"sortable_name":"Floyd, Elmore, ","death_year":null},{"id":9362,"created_at":"2025-06-06T23:24:21.485Z","updated_at":"2025-06-06T23:24:21.485Z","last_name":"Robertson","first_name":"Mittie","middle_name":"M","sex":"Female","race":"Black","name_prefix":null,"name_suffix":null,"searchable_name":"Mittie M Robertson","birth_year":1885,"is_birth_year_estimated":true,"pob":"Tennessee","is_pob_estimated":true,"notes":null,"description":null,"sortable_name":"Robertson, Mittie, M","death_year":null}]}},
{"type":"Feature","geometry":{"type":"Point","coordinates":[-95.9862825,36.1605345]},"properties":{"location_id":771,"year":"1920","title":"121 N Greenwood Street","addresses":[{"id":771,"building_id":771,"is_primary":true,"house_number":"121","prefix":"N","name":"Greenwood Street","suffix":null,"city":"Tulsa","postal_code":null,"created_at":"2025-06-06T22:57:51.894Z","updated_at":"2025-06-06T22:57:51.894Z","year":null,"searchable_text":"121 N Greenwood Street  Tulsa"}],"audios":[],"stories":[{"record":{"id":8,"created_by_id":2,"reviewed_by_id":null,"reviewed_at":null,"weight":0,"source":null,"notes":"","date_type":null,"date_text":null,"date_start":null,"date_end":null,"created_at":"2025-06-17T22:20:25.189Z","updated_at":"2025-06-17T22:20:25.197Z","searchable_text":null},"sources":{"id":25,"name":"sources","body":"<div>New York Times</div>","record_type":"Narrative","record_id":8,"created_at":"2025-06-17T22:20:25.196Z","updated_at":"2025-06-17T22:20:25.196Z"},"story":{"id":24,"name":"story","body":"<div><strong>James Nails</strong>...and his brother <strong>Henry</strong> ran a shoe shop in the Gist Building at 121 Greenwood Avenue. The shop carried Black Swan records, and the family also owned a dance pavilion and skating rink in the community.</div>","record_type":"Narrative","record_id":8,"created_at":"2025-06-17T22:20:25.194Z","updated_at":"2025-06-17T22:20:25.194Z"}}],"videos":[],"photos":[],"documents":[],"description":"<i data-poi></i>","rich_description":{"id":26,"name":"description","body":"<pre>&lt;i data-poi&gt;&lt;/i&gt;</pre>","record_type":"Building","record_id":771,"created_at":"2025-06-17T22:20:42.377Z","updated_at":"2025-06-17T22:20:42.377Z"},"census_records":[],"people":[{"id":8374,"created_at":"2025-06-06T23:23:04.588Z","updated_at":"2025-06-06T23:23:04.588Z","last_name":"Gist","first_name":"John","middle_name":"S","sex":"Male","race":"Black","name_prefix":null,"name_suffix":null,"searchable_name":"John S Gist","birth_year":1867,"is_birth_year_estimated":true,"pob":"South Carolina","is_pob_estimated":true,"notes":null,"description":null,"sortable_name":"Gist, John, S","death_year":null},{"id":8375,"created_at":"2025-06-06T23:23:04.664Z","updated_at":"2025-06-06T23:23:04.664Z","last_name":"Gist","first_name":"Alice","middle_name":"M","sex":"Female","race":"Black","name_prefix":null,"name_suffix":null,"searchable_name":"Alice M Gist","birth_year":1871,"is_birth_year_estimated":true,"pob":"Louisiana","is_pob_estimated":true,"notes":null,"description":null,"sortable_name":"Gist, Alice, M","death_year":null},{"id":8376,"created_at":"2025-06-06T23:23:04.740Z","updated_at":"2025-06-06T23:23:04.740Z","last_name":"Gist","first_name":"John","middle_name":"S","sex":"Male","race":"Black","name_prefix":null,"name_suffix":null,"searchable_name":"John S Gist","birth_year":1914,"is_birth_year_estimated":true,"pob":"Nevada","is_pob_estimated":true,"notes":null,"description":null,"sortable_name":"Gist, John, S","death_year":null},{"id":8377,"created_at":"2025-06-06T23:23:04.842Z","updated_at":"2025-06-06T23:23:04.842Z","last_name":"Fesler","first_name":"Lucille","middle_name":null,"sex":"Female","race":"Black","name_prefix":null,"name_suffix":null,"searchable_name":"Lucille Fesler","birth_year":1908,"is_birth_year_estimated":true,"pob":"Oklahoma","is_pob_estimated":true,"notes":null,"description":null,"sortable_name":"Fesler, Lucille, ","death_year":null},{"id":8378,"created_at":"2025-06-06T23:23:04.927Z","updated_at":"2025-06-06T23:23:04.927Z","last_name":"Drake","first_name":"Richard","middle_name":"L","sex":"Male","race":"Black","name_prefix":null,"name_suffix":null,"searchable_name":"Richard L Drake","birth_year":1891,"is_birth_year_estimated":true,"pob":"Kansas","is_pob_estimated":true,"notes":null,"description":null,"sortable_name":"Drake, Richard, L","death_year":null},{"id":8379,"created_at":"2025-06-06T23:23:05.007Z","updated_at":"2025-06-06T23:23:05.007Z","last_name":"Wright","first_name":"Jerry","middle_name":"M","sex":"Male","race":"Black","name_prefix":null,"name_suffix":null,"searchable_name":"Jerry M Wright","birth_year":1886,"is_birth_year_estimated":true,"pob":"Alabama","is_pob_estimated":true,"notes":null,"description":null,"sortable_name":"Wright, Jerry, M","death_year":null},{"id":8380,"created_at":"2025-06-06T23:23:05.091Z","updated_at":"2025-06-06T23:23:05.091Z","last_name":"Washington","first_name":"Floyd","middle_name":null,"sex":"Male","race":"Black","name_prefix":null,"name_suffix":null,"searchable_name":"Floyd Washington","birth_year":1889,"is_birth_year_estimated":true,"pob":"Texas","is_pob_estimated":true,"notes":null,"description":null,"sortable_name":"Washington, Floyd, ","death_year":null},{"id":8381,"created_at":"2025-06-06T23:23:05.171Z","updated_at":"2025-06-06T23:23:05.171Z","last_name":"Washington","first_name":"Sadie","middle_name":null,"sex":"Female","race":"Black","name_prefix":null,"name_suffix":null,"searchable_name":"Sadie Washington","birth_year":1894,"is_birth_year_estimated":true,"pob":"Texas","is_pob_estimated":true,"notes":null,"description":null,"sortable_name":"Washington, Sadie, ","death_year":null},{"id":8382,"created_at":"2025-06-06T23:23:05.256Z","updated_at":"2025-06-06T23:23:05.256Z","last_name":"Swanson","first_name":"Willie","middle_name":null,"sex":"Female","race":"Black","name_prefix":null,"name_suffix":null,"searchable_name":"Willie Swanson","birth_year":1893,"is_birth_year_estimated":true,"pob":"Oklahoma","is_pob_estimated":true,"notes":null,"description":null,"sortable_name":"Swanson, Willie, ","death_year":null},{"id":9354,"created_at":"2025-06-06T23:24:20.908Z","updated_at":"2025-06-06T23:24:20.908Z","last_name":"Washington","first_name":"Searvia","middle_name":null,"sex":"Female","race":"Black","name_prefix":null,"name_suffix":null,"searchable_name":"Searvia Washington","birth_year":1910,"is_birth_year_estimated":true,"pob":"Texas","is_pob_estimated":true,"notes":null,"description":null,"sortable_name":"Washington, Searvia, ","death_year":null}]}},
{"type":"Feature","geometry":{"type":"Point","coordinates":[-95.985537,36.1624353]},"properties":{"location_id":897,"year":"1920","title":"326 N Hartford Street","addresses":[{"id":897,"building_id":897,"is_primary":true,"house_number":"326","prefix":"N","name":"Hartford","suffix":"Ave","city":"Tulsa","postal_code":null,"created_at":"2025-06-06T22:58:17.529Z","updated_at":"2025-06-17T19:38:44.732Z","year":null,"searchable_text":"326 N Hartford Ave Tulsa"}],"audios":[],"stories":[{"record":{"id":2,"created_by_id":2,"reviewed_by_id":2,"reviewed_at":"2025-06-17T19:43:09.771Z","weight":0,"source":null,"notes":"","date_type":null,"date_text":null,"date_start":null,"date_end":null,"created_at":"2025-06-17T19:42:59.859Z","updated_at":"2025-06-17T19:43:09.775Z","searchable_text":null},"sources":{"id":7,"name":"sources","body":"<div>Historic Tulsa, https://historictulsa.blogspot.com/</div>","record_type":"Narrative","record_id":2,"created_at":"2025-06-17T19:42:59.867Z","updated_at":"2025-06-17T19:42:59.867Z"},"story":{"id":6,"name":"story","body":"<div>In the fall of 1913, Dunbar Grade School began operation in an eighteen-room brick building and a two-room frame building located at 326 N. Hartford Avenue. That first year’s enrollment included 241 lower grade students and 7 high school students.</div>","record_type":"Narrative","record_id":2,"created_at":"2025-06-17T19:42:59.865Z","updated_at":"2025-06-17T19:42:59.865Z"}}],"videos":[],"photos":[],"documents":[],"description":"<i data-poi></i>","rich_description":{"id":5,"name":"description","body":"<pre>&lt;i data-poi&gt;&lt;/i&gt;</pre>","record_type":"Building","record_id":897,"created_at":"2025-06-17T19:34:43.030Z","updated_at":"2025-06-17T19:38:44.729Z"},"census_records":[],"people":[{"id":8997,"created_at":"2025-06-06T23:23:53.542Z","updated_at":"2025-06-06T23:23:53.542Z","last_name":"Sandridge","first_name":"B","middle_name":"J","sex":"Female","race":"Black","name_prefix":null,"name_suffix":null,"searchable_name":"B J Sandridge","birth_year":1882,"is_birth_year_estimated":true,"pob":"Oklahoma","is_pob_estimated":true,"notes":null,"description":null,"sortable_name":"Sandridge, B, J","death_year":null},{"id":9385,"created_at":"2025-06-06T23:24:23.156Z","updated_at":"2025-06-06T23:24:23.156Z","last_name":"Sandridge","first_name":"Matt","middle_name":null,"sex":"Male","race":"Black","name_prefix":null,"name_suffix":null,"searchable_name":"Matt Sandridge","birth_year":1880,"is_birth_year_estimated":true,"pob":"Oklahoma","is_pob_estimated":true,"notes":null,"description":null,"sortable_name":"Sandridge, Matt, ","death_year":null}]}},
{"type":"Feature","geometry":{"type":"Point","coordinates":[-95.9864122,36.1602142]},"properties":{"location_id":891,"year":"1920","title":"Gurley Hotel","addresses":[{"id":891,"building_id":891,"is_primary":true,"house_number":"112","prefix":"N","name":"Greenwood","suffix":"Ave","city":"Tulsa","postal_code":null,"created_at":"2025-06-06T22:58:16.255Z","updated_at":"2025-06-17T20:04:15.347Z","year":null,"searchable_text":"112 N Greenwood Ave Tulsa"}],"audios":[],"stories":[],"videos":[],"photos":[],"documents":[],"description":"<i data-poi></i>","rich_description":{"id":8,"name":"description","body":"<pre>&lt;i data-poi&gt;&lt;/i&gt;</pre>","record_type":"Building","record_id":891,"created_at":"2025-06-17T20:04:15.345Z","updated_at":"2025-06-17T20:04:15.345Z"},"census_records":[],"people":[{"id":8963,"created_at":"2025-06-06T23:23:50.947Z","updated_at":"2025-06-06T23:23:50.947Z","last_name":"Williams","first_name":"Archie","middle_name":null,"sex":"Male","race":"Mulatto","name_prefix":null,"name_suffix":null,"searchable_name":"Archie Williams","birth_year":1884,"is_birth_year_estimated":true,"pob":"Louisiana","is_pob_estimated":true,"notes":null,"description":null,"sortable_name":"Williams, Archie, ","death_year":null}]}},
{"type":"Feature","geometry":{"type":"Point","coordinates":[-95.9856027,36.159893]},"properties":{"location_id":785,"year":"1920","title":"612 E Archer Street","addresses":[{"id":785,"building_id":785,"is_primary":true,"house_number":"612","prefix":"E","name":"Archer","suffix":"St","city":"Tulsa","postal_code":null,"created_at":"2025-06-06T22:57:54.963Z","updated_at":"2025-06-17T21:38:53.114Z","year":null,"searchable_text":"612 E Archer St Tulsa"}],"audios":[],"stories":[{"record":{"id":3,"created_by_id":2,"reviewed_by_id":2,"reviewed_at":"2025-06-17T21:52:47.320Z","weight":0,"source":null,"notes":"","date_type":null,"date_text":null,"date_start":null,"date_end":null,"created_at":"2025-06-17T21:40:42.687Z","updated_at":"2025-06-17T21:52:47.323Z","searchable_text":null},"sources":{"id":11,"name":"sources","body":"<div>The Victory of Greenwood</div>","record_type":"Narrative","record_id":3,"created_at":"2025-06-17T21:40:42.693Z","updated_at":"2025-06-17T21:40:42.693Z"},"story":{"id":10,"name":"story","body":"<div>After Mabel Little opened her business in Tulsa, she received a certification from Madam C.J. Walker’s beauty course, and by 1918, her company was booming. Little relocated the Little Rose Beauty Salon to <strong>612 E. Archer St. </strong>There, she hired a staff of three beauticians and had built a clientele of over six hundred. <br><br>An article in <em>Ebony </em>magazine describes that Thursday nights were, “Maid’s Night Out” in Greenwood—the one day a week that servants of the white community would be allowed to take the evening off and enjoy themselves. Young ladies would come to Mabel Little to look their best, knowing that she had, “her magic touch.”</div>","record_type":"Narrative","record_id":3,"created_at":"2025-06-17T21:40:42.691Z","updated_at":"2025-06-17T21:40:42.691Z"}}],"videos":[],"photos":[],"documents":[],"description":"<i data-poi></i>","rich_description":{"id":9,"name":"description","body":"<pre>&lt;i data-poi&gt;&lt;/i&gt;</pre>","record_type":"Building","record_id":785,"created_at":"2025-06-17T21:38:53.111Z","updated_at":"2025-06-17T21:38:53.111Z"},"census_records":[],"people":[{"id":8455,"created_at":"2025-06-06T23:23:12.172Z","updated_at":"2025-06-06T23:23:12.172Z","last_name":"Hudson","first_name":"Henry","middle_name":"W","sex":"Male","race":"Black","name_prefix":null,"name_suffix":null,"searchable_name":"Henry W Hudson","birth_year":1866,"is_birth_year_estimated":true,"pob":"Arkansas","is_pob_estimated":true,"notes":null,"description":null,"sortable_name":"Hudson, Henry, W","death_year":null},{"id":8456,"created_at":"2025-06-06T23:23:12.276Z","updated_at":"2025-06-06T23:23:12.276Z","last_name":"Hudson","first_name":"Lela","middle_name":null,"sex":"Female","race":"Black","name_prefix":null,"name_suffix":null,"searchable_name":"Lela Hudson","birth_year":1875,"is_birth_year_estimated":true,"pob":"Alabama","is_pob_estimated":true,"notes":null,"description":null,"sortable_name":"Hudson, Lela, ","death_year":null},{"id":8457,"created_at":"2025-06-06T23:23:12.350Z","updated_at":"2025-06-06T23:23:12.350Z","last_name":"Hulsey","first_name":"Vivian","middle_name":null,"sex":"Female","race":"Black","name_prefix":null,"name_suffix":null,"searchable_name":"Vivian Hulsey","birth_year":1912,"is_birth_year_estimated":true,"pob":"Missouri","is_pob_estimated":true,"notes":null,"description":null,"sortable_name":"Hulsey, Vivian, ","death_year":null},{"id":8973,"created_at":"2025-06-06T23:23:51.717Z","updated_at":"2025-06-06T23:23:51.717Z","last_name":"Childers","first_name":"Knox","middle_name":null,"sex":"Male","race":"Black","name_prefix":null,"name_suffix":null,"searchable_name":"Knox Childers","birth_year":1897,"is_birth_year_estimated":true,"pob":"Texas","is_pob_estimated":true,"notes":null,"description":null,"sortable_name":"Childers, Knox, ","death_year":null},{"id":8974,"created_at":"2025-06-06T23:23:51.790Z","updated_at":"2025-06-06T23:23:51.790Z","last_name":"O'Bannon","first_name":"Matine","middle_name":null,"sex":"Female","race":"Black","name_prefix":null,"name_suffix":null,"searchable_name":"Matine O'Bannon","birth_year":1900,"is_birth_year_estimated":true,"pob":"Texas","is_pob_estimated":true,"notes":null,"description":null,"sortable_name":"O'Bannon, Matine, ","death_year":null},{"id":8975,"created_at":"2025-06-06T23:23:51.864Z","updated_at":"2025-06-06T23:23:51.864Z","last_name":"O'Bannon","first_name":"James","middle_name":null,"sex":"Male","race":"Black","name_prefix":null,"name_suffix":null,"searchable_name":"James O'Bannon","birth_year":1890,"is_birth_year_estimated":true,"pob":"Texas","is_pob_estimated":true,"notes":null,"description":null,"sortable_name":"O'Bannon, James, ","death_year":null},{"id":8976,"created_at":"2025-06-06T23:23:51.939Z","updated_at":"2025-06-06T23:23:51.939Z","last_name":"Steel","first_name":"Hazel","middle_name":null,"sex":"Female","race":"Black","name_prefix":null,"name_suffix":null,"searchable_name":"Hazel Steel","birth_year":1888,"is_birth_year_estimated":true,"pob":"South Carolina","is_pob_estimated":true,"notes":null,"description":null,"sortable_name":"Steel, Hazel, ","death_year":null}]}},
{"type":"Feature","geometry":{"type":"Point","coordinates":[-95.9865072,36.1613145]},"properties":{"location_id":890,"year":"1920","title":"Stradford Hotel","addresses":[{"id":890,"building_id":890,"is_primary":true,"house_number":"301","prefix":"N","name":"Greenwood","suffix":"Ave","city":"Tulsa","postal_code":null,"created_at":"2025-06-06T22:58:14.923Z","updated_at":"2025-06-17T21:51:06.776Z","year":null,"searchable_text":"301 N Greenwood Ave Tulsa"}],"audios":[],"stories":[{"record":{"id":4,"created_by_id":2,"reviewed_by_id":2,"reviewed_at":"2025-06-17T21:52:53.242Z","weight":0,"source":null,"notes":"","date_type":"year","date_text":"2020","date_start":null,"date_end":null,"created_at":"2025-06-17T21:52:28.703Z","updated_at":"2025-06-17T21:52:53.247Z","searchable_text":null},"sources":{"id":14,"name":"sources","body":"<div>Euell Dixon, Blackpast.org</div>","record_type":"Narrative","record_id":4,"created_at":"2025-06-17T21:52:28.709Z","updated_at":"2025-06-17T21:52:28.709Z"},"story":{"id":13,"name":"story","body":"<div>On June 1, 1918 Stradford opened the luxurious fifty-four room Stradford Hotel at 301 N. Greenwood Avenue. It was the largest black owned and operated hotel in Oklahoma and one of the few black-owned hotels in the United States. The Stradford had a dining hall, a gambling room, a saloon, and a large hall for events such as live music. By 1920 Stradford had become the richest black man in Tulsa, owning over fifteen rental properties and an apartment building, along with the hotel.<br><br></div>","record_type":"Narrative","record_id":4,"created_at":"2025-06-17T21:52:28.707Z","updated_at":"2025-06-17T21:52:28.707Z"}},{"record":{"id":5,"created_by_id":2,"reviewed_by_id":2,"reviewed_at":"2025-06-17T21:54:46.685Z","weight":0,"source":null,"notes":"","date_type":"year","date_text":"2021","date_start":null,"date_end":null,"created_at":"2025-06-17T21:54:43.349Z","updated_at":"2025-06-17T21:54:46.688Z","searchable_text":null},"sources":{"id":16,"name":"sources","body":"<div>The Victory of Greenwood</div>","record_type":"Narrative","record_id":5,"created_at":"2025-06-17T21:54:43.355Z","updated_at":"2025-06-17T21:54:43.355Z"},"story":{"id":15,"name":"story","body":"<div>Upon his arrival in Greenwood, J.B. Stradford quickly found a kindred spirit in O.W. Gurley. The two men formed an informal business partnership by investing in land, building rental homes, and selling it to other Black entrepreneurs. Over the next 18 years, Stradford amassed a sizable fortune.<em> </em>In <em>The Events of the Tulsa Disaster</em>, Mary E. Jones Parish documented the value of Stradford’s home at $125,000, the Stradford Hotel at $50,000, and another 2-story brick residence on N. Elgin Ave. at $3,000.&nbsp;</div>","record_type":"Narrative","record_id":5,"created_at":"2025-06-17T21:54:43.353Z","updated_at":"2025-06-17T21:54:43.353Z"}}],"videos":[],"photos":[],"documents":[],"description":"<i data-poi></i>","rich_description":{"id":12,"name":"description","body":"<pre>&lt;i data-poi&gt;&lt;/i&gt;</pre>","record_type":"Building","record_id":890,"created_at":"2025-06-17T21:51:06.773Z","updated_at":"2025-06-17T21:51:06.773Z"},"census_records":[],"people":[{"id":8921,"created_at":"2025-06-06T23:23:47.836Z","updated_at":"2025-06-06T23:23:47.836Z","last_name":"Stradford","first_name":"Augusta","middle_name":"L","sex":"Female","race":"Black","name_prefix":null,"name_suffix":null,"searchable_name":"Augusta L Stradford","birth_year":1885,"is_birth_year_estimated":true,"pob":"Mississippi","is_pob_estimated":true,"notes":null,"description":null,"sortable_name":"Stradford, Augusta, L","death_year":null},{"id":8922,"created_at":"2025-06-06T23:23:47.909Z","updated_at":"2025-06-06T23:23:47.909Z","last_name":"Stradford","first_name":"John","middle_name":"E","sex":"Male","race":"Black","name_prefix":null,"name_suffix":null,"searchable_name":"John E Stradford","birth_year":1886,"is_birth_year_estimated":true,"pob":"Kentucky","is_pob_estimated":true,"notes":null,"description":null,"sortable_name":"Stradford, John, E","death_year":null},{"id":8923,"created_at":"2025-06-06T23:23:47.981Z","updated_at":"2025-06-06T23:23:47.981Z","last_name":"Stradford","first_name":"Annie","middle_name":null,"sex":"Female","race":"Black","name_prefix":null,"name_suffix":null,"searchable_name":"Annie Stradford","birth_year":1892,"is_birth_year_estimated":true,"pob":"Texas","is_pob_estimated":true,"notes":null,"description":null,"sortable_name":"Stradford, Annie, ","death_year":null},{"id":8924,"created_at":"2025-06-06T23:23:48.051Z","updated_at":"2025-06-06T23:23:48.051Z","last_name":"Wyands","first_name":"Francis","middle_name":null,"sex":"Male","race":"Black","name_prefix":null,"name_suffix":null,"searchable_name":"Francis Wyands","birth_year":1886,"is_birth_year_estimated":true,"pob":"Louisiana","is_pob_estimated":true,"notes":null,"description":null,"sortable_name":"Wyands, Francis, ","death_year":null},{"id":8925,"created_at":"2025-06-06T23:23:48.120Z","updated_at":"2025-06-06T23:23:48.120Z","last_name":"Wyands","first_name":"Alma","middle_name":null,"sex":"Female","race":"Black","name_prefix":null,"name_suffix":null,"searchable_name":"Alma Wyands","birth_year":1888,"is_birth_year_estimated":true,"pob":"Arkansas","is_pob_estimated":true,"notes":null,"description":null,"sortable_name":"Wyands, Alma, ","death_year":null},{"id":8926,"created_at":"2025-06-06T23:23:48.189Z","updated_at":"2025-06-06T23:23:48.189Z","last_name":"Mcmillan","first_name":"George","middle_name":"H","sex":"Male","race":"Black","name_prefix":null,"name_suffix":null,"searchable_name":"George H Mcmillan","birth_year":1892,"is_birth_year_estimated":true,"pob":"Missouri","is_pob_estimated":true,"notes":null,"description":null,"sortable_name":"Mcmillan, George, H","death_year":null},{"id":8927,"created_at":"2025-06-06T23:23:48.258Z","updated_at":"2025-06-06T23:23:48.258Z","last_name":"Robinson","first_name":"W","middle_name":"J","sex":"Male","race":"Black","name_prefix":null,"name_suffix":null,"searchable_name":"W J Robinson","birth_year":1894,"is_birth_year_estimated":true,"pob":"Texas","is_pob_estimated":true,"notes":null,"description":null,"sortable_name":"Robinson, W, J","death_year":null},{"id":8928,"created_at":"2025-06-06T23:23:48.327Z","updated_at":"2025-06-06T23:23:48.327Z","last_name":"Gamble","first_name":"Harry","middle_name":null,"sex":"Male","race":"Black","name_prefix":null,"name_suffix":null,"searchable_name":"Harry Gamble","birth_year":1897,"is_birth_year_estimated":true,"pob":"Texas","is_pob_estimated":true,"notes":null,"description":null,"sortable_name":"Gamble, Harry, ","death_year":null},{"id":8929,"created_at":"2025-06-06T23:23:48.401Z","updated_at":"2025-06-06T23:23:48.401Z","last_name":"Webber","first_name":"Willa","middle_name":"B","sex":"Female","race":"Black","name_prefix":null,"name_suffix":null,"searchable_name":"Willa B Webber","birth_year":1899,"is_birth_year_estimated":true,"pob":"Oklahoma","is_pob_estimated":true,"notes":null,"description":null,"sortable_name":"Webber, Willa, B","death_year":null},{"id":8930,"created_at":"2025-06-06T23:23:48.472Z","updated_at":"2025-06-06T23:23:48.472Z","last_name":"Shorter","first_name":"Arthur","middle_name":"C","sex":"Male","race":"Black","name_prefix":null,"name_suffix":null,"searchable_name":"Arthur C Shorter","birth_year":1886,"is_birth_year_estimated":true,"pob":"Indiana","is_pob_estimated":true,"notes":null,"description":null,"sortable_name":"Shorter, Arthur, C","death_year":null},{"id":8931,"created_at":"2025-06-06T23:23:48.543Z","updated_at":"2025-06-06T23:23:48.543Z","last_name":"Walker","first_name":"Harry","middle_name":"G","sex":"Male","race":"Black","name_prefix":null,"name_suffix":null,"searchable_name":"Harry G Walker","birth_year":1897,"is_birth_year_estimated":true,"pob":"Kansas","is_pob_estimated":true,"notes":null,"description":null,"sortable_name":"Walker, Harry, G","death_year":null},{"id":8932,"created_at":"2025-06-06T23:23:48.618Z","updated_at":"2025-06-06T23:23:48.618Z","last_name":"Wesson","first_name":"J","middle_name":"T","sex":"Male","race":"Black","name_prefix":null,"name_suffix":null,"searchable_name":"J T Wesson","birth_year":1889,"is_birth_year_estimated":true,"pob":"Montana","is_pob_estimated":true,"notes":null,"description":null,"sortable_name":"Wesson, J, T","death_year":null},{"id":8933,"created_at":"2025-06-06T23:23:48.692Z","updated_at":"2025-06-06T23:23:48.692Z","last_name":"Mcbee","first_name":"Rose","middle_name":"L","sex":"Female","race":"Black","name_prefix":null,"name_suffix":null,"searchable_name":"Rose L Mcbee","birth_year":1899,"is_birth_year_estimated":true,"pob":"Kansas","is_pob_estimated":true,"notes":null,"description":null,"sortable_name":"Mcbee, Rose, L","death_year":null},{"id":8934,"created_at":"2025-06-06T23:23:48.763Z","updated_at":"2025-06-06T23:23:48.763Z","last_name":"Lamar","first_name":"Beulah","middle_name":null,"sex":"Female","race":"Black","name_prefix":null,"name_suffix":null,"searchable_name":"Beulah Lamar","birth_year":1889,"is_birth_year_estimated":true,"pob":"Texas","is_pob_estimated":true,"notes":null,"description":null,"sortable_name":"Lamar, Beulah, ","death_year":null},{"id":8935,"created_at":"2025-06-06T23:23:48.832Z","updated_at":"2025-06-06T23:23:48.832Z","last_name":"Holmes","first_name":"W","middle_name":"G","sex":"Male","race":"Black","name_prefix":null,"name_suffix":null,"searchable_name":"W G Holmes","birth_year":1880,"is_birth_year_estimated":true,"pob":"Missouri","is_pob_estimated":true,"notes":null,"description":null,"sortable_name":"Holmes, W, G","death_year":null},{"id":8936,"created_at":"2025-06-06T23:23:48.899Z","updated_at":"2025-06-06T23:23:48.899Z","last_name":"Stewart","first_name":"R","middle_name":"W","sex":"Male","race":"Black","name_prefix":null,"name_suffix":null,"searchable_name":"R W Stewart","birth_year":1885,"is_birth_year_estimated":true,"pob":"Texas","is_pob_estimated":true,"notes":null,"description":null,"sortable_name":"Stewart, R, W","death_year":null},{"id":8937,"created_at":"2025-06-06T23:23:49.004Z","updated_at":"2025-06-06T23:23:49.004Z","last_name":"Hatler","first_name":"W","middle_name":"L","sex":"Male","race":"Black","name_prefix":null,"name_suffix":null,"searchable_name":"W L Hatler","birth_year":1887,"is_birth_year_estimated":true,"pob":"Connecticut","is_pob_estimated":true,"notes":null,"description":null,"sortable_name":"Hatler, W, L","death_year":null},{"id":8938,"created_at":"2025-06-06T23:23:49.082Z","updated_at":"2025-06-06T23:23:49.082Z","last_name":"Ridge","first_name":"Stephen","middle_name":"E","sex":"Male","race":"Black","name_prefix":null,"name_suffix":null,"searchable_name":"Stephen E Ridge","birth_year":1885,"is_birth_year_estimated":true,"pob":"Missouri","is_pob_estimated":true,"notes":null,"description":null,"sortable_name":"Ridge, Stephen, E","death_year":null},{"id":8939,"created_at":"2025-06-06T23:23:49.156Z","updated_at":"2025-06-06T23:23:49.156Z","last_name":"Smith","first_name":"Millard","middle_name":null,"sex":"Male","race":"Black","name_prefix":null,"name_suffix":null,"searchable_name":"Millard Smith","birth_year":1899,"is_birth_year_estimated":true,"pob":"Oklahoma","is_pob_estimated":true,"notes":null,"description":null,"sortable_name":"Smith, Millard, ","death_year":null},{"id":8940,"created_at":"2025-06-06T23:23:49.226Z","updated_at":"2025-06-06T23:23:49.226Z","last_name":"Walker","first_name":"John","middle_name":"S","sex":"Male","race":"Black","name_prefix":null,"name_suffix":null,"searchable_name":"John S Walker","birth_year":1903,"is_birth_year_estimated":true,"pob":"Texas","is_pob_estimated":true,"notes":null,"description":null,"sortable_name":"Walker, John, S","death_year":null},{"id":8941,"created_at":"2025-06-06T23:23:49.313Z","updated_at":"2025-06-06T23:23:49.313Z","last_name":"Casheart","first_name":"P","middle_name":"H","sex":"Male","race":"Black","name_prefix":null,"name_suffix":null,"searchable_name":"P H Casheart","birth_year":1900,"is_birth_year_estimated":true,"pob":"Texas","is_pob_estimated":true,"notes":null,"description":null,"sortable_name":"Casheart, P, H","death_year":null},{"id":8942,"created_at":"2025-06-06T23:23:49.386Z","updated_at":"2025-06-06T23:23:49.386Z","last_name":"Ayers","first_name":"Eugene","middle_name":null,"sex":"Male","race":"Black","name_prefix":null,"name_suffix":null,"searchable_name":"Eugene Ayers","birth_year":1897,"is_birth_year_estimated":true,"pob":"Kansas","is_pob_estimated":true,"notes":null,"description":null,"sortable_name":"Ayers, Eugene, ","death_year":null},{"id":8943,"created_at":"2025-06-06T23:23:49.464Z","updated_at":"2025-06-06T23:23:49.464Z","last_name":"Timer","first_name":"S","middle_name":"Q","sex":"Male","race":"Black","name_prefix":null,"name_suffix":null,"searchable_name":"S Q Timer","birth_year":1893,"is_birth_year_estimated":true,"pob":"Mississippi","is_pob_estimated":true,"notes":null,"description":null,"sortable_name":"Timer, S, Q","death_year":null},{"id":8944,"created_at":"2025-06-06T23:23:49.542Z","updated_at":"2025-06-06T23:23:49.542Z","last_name":"Brooks","first_name":"B","middle_name":"G","sex":"Male","race":"Black","name_prefix":null,"name_suffix":null,"searchable_name":"B G Brooks","birth_year":1884,"is_birth_year_estimated":true,"pob":"Louisiana","is_pob_estimated":true,"notes":null,"description":null,"sortable_name":"Brooks, B, G","death_year":null},{"id":8945,"created_at":"2025-06-06T23:23:49.613Z","updated_at":"2025-06-06T23:23:49.613Z","last_name":"Hodges","first_name":"Thomas","middle_name":null,"sex":"Male","race":"Black","name_prefix":null,"name_suffix":null,"searchable_name":"Thomas Hodges","birth_year":1900,"is_birth_year_estimated":true,"pob":"Oklahoma","is_pob_estimated":true,"notes":null,"description":null,"sortable_name":"Hodges, Thomas, ","death_year":null},{"id":8946,"created_at":"2025-06-06T23:23:49.683Z","updated_at":"2025-06-06T23:23:49.683Z","last_name":"Kirk","first_name":"Willie","middle_name":"L","sex":"Male","race":"Black","name_prefix":null,"name_suffix":null,"searchable_name":"Willie L Kirk","birth_year":1898,"is_birth_year_estimated":true,"pob":"Texas","is_pob_estimated":true,"notes":null,"description":null,"sortable_name":"Kirk, Willie, L","death_year":null},{"id":8947,"created_at":"2025-06-06T23:23:49.756Z","updated_at":"2025-06-06T23:23:49.756Z","last_name":"Mc Kurkin","first_name":"William","middle_name":null,"sex":"Male","race":"Black","name_prefix":null,"name_suffix":null,"searchable_name":"William Mc Kurkin","birth_year":1898,"is_birth_year_estimated":true,"pob":"Arkansas","is_pob_estimated":true,"notes":null,"description":null,"sortable_name":"Mc Kurkin, William, ","death_year":null},{"id":8948,"created_at":"2025-06-06T23:23:49.826Z","updated_at":"2025-06-06T23:23:49.826Z","last_name":"Holmes","first_name":"Fannie","middle_name":null,"sex":"Female","race":"Black","name_prefix":null,"name_suffix":null,"searchable_name":"Fannie Holmes","birth_year":1888,"is_birth_year_estimated":true,"pob":"Oklahoma","is_pob_estimated":true,"notes":null,"description":null,"sortable_name":"Holmes, Fannie, ","death_year":null},{"id":8949,"created_at":"2025-06-06T23:23:49.899Z","updated_at":"2025-06-06T23:23:49.899Z","last_name":"Hodo","first_name":"John","middle_name":"S","sex":"Male","race":"Black","name_prefix":null,"name_suffix":null,"searchable_name":"John S Hodo","birth_year":1880,"is_birth_year_estimated":true,"pob":"Georgia","is_pob_estimated":true,"notes":null,"description":null,"sortable_name":"Hodo, John, S","death_year":null},{"id":8950,"created_at":"2025-06-06T23:23:49.978Z","updated_at":"2025-06-06T23:23:49.978Z","last_name":"Hodo","first_name":"Flossie","middle_name":"L","sex":"Female","race":"Black","name_prefix":null,"name_suffix":null,"searchable_name":"Flossie L Hodo","birth_year":1904,"is_birth_year_estimated":true,"pob":"Tennessee","is_pob_estimated":true,"notes":null,"description":null,"sortable_name":"Hodo, Flossie, L","death_year":null},{"id":8951,"created_at":"2025-06-06T23:23:50.049Z","updated_at":"2025-06-06T23:23:50.049Z","last_name":"Gowdrill","first_name":"Alonzo","middle_name":null,"sex":"Male","race":"Black","name_prefix":null,"name_suffix":null,"searchable_name":"Alonzo Gowdrill","birth_year":1896,"is_birth_year_estimated":true,"pob":"Oklahoma","is_pob_estimated":true,"notes":null,"description":null,"sortable_name":"Gowdrill, Alonzo, ","death_year":null},{"id":8952,"created_at":"2025-06-06T23:23:50.121Z","updated_at":"2025-06-06T23:23:50.121Z","last_name":"Matleslie","first_name":"Robinson","middle_name":null,"sex":"Male","race":"Black","name_prefix":null,"name_suffix":null,"searchable_name":"Robinson Matleslie","birth_year":1886,"is_birth_year_estimated":true,"pob":"Oklahoma","is_pob_estimated":true,"notes":null,"description":null,"sortable_name":"Matleslie, Robinson, ","death_year":null},{"id":8953,"created_at":"2025-06-06T23:23:50.201Z","updated_at":"2025-06-06T23:23:50.201Z","last_name":"Holman","first_name":"G","middle_name":"T","sex":"Male","race":"Black","name_prefix":null,"name_suffix":null,"searchable_name":"G T Holman","birth_year":1896,"is_birth_year_estimated":true,"pob":"Arkansas","is_pob_estimated":true,"notes":null,"description":null,"sortable_name":"Holman, G, T","death_year":null},{"id":8954,"created_at":"2025-06-06T23:23:50.280Z","updated_at":"2025-06-06T23:23:50.280Z","last_name":"Robinson","first_name":"Beatrice","middle_name":null,"sex":"Female","race":"Black","name_prefix":null,"name_suffix":null,"searchable_name":"Beatrice Robinson","birth_year":1898,"is_birth_year_estimated":true,"pob":"Kansas","is_pob_estimated":true,"notes":null,"description":null,"sortable_name":"Robinson, Beatrice, ","death_year":null},{"id":8955,"created_at":"2025-06-06T23:23:50.354Z","updated_at":"2025-06-06T23:23:50.354Z","last_name":"James","first_name":"Alberta","middle_name":null,"sex":"Female","race":"Black","name_prefix":null,"name_suffix":null,"searchable_name":"Alberta James","birth_year":1897,"is_birth_year_estimated":true,"pob":"Texas","is_pob_estimated":true,"notes":null,"description":null,"sortable_name":"James, Alberta, ","death_year":null},{"id":8956,"created_at":"2025-06-06T23:23:50.429Z","updated_at":"2025-06-06T23:23:50.429Z","last_name":"Riley","first_name":"Edna","middle_name":null,"sex":"Female","race":"Black","name_prefix":null,"name_suffix":null,"searchable_name":"Edna Riley","birth_year":1901,"is_birth_year_estimated":true,"pob":"Texas","is_pob_estimated":true,"notes":null,"description":null,"sortable_name":"Riley, Edna, ","death_year":null},{"id":8957,"created_at":"2025-06-06T23:23:50.513Z","updated_at":"2025-06-06T23:23:50.513Z","last_name":"Riley","first_name":"Velma","middle_name":null,"sex":"Female","race":"Black","name_prefix":null,"name_suffix":null,"searchable_name":"Velma Riley","birth_year":1896,"is_birth_year_estimated":true,"pob":"Texas","is_pob_estimated":true,"notes":null,"description":null,"sortable_name":"Riley, Velma, ","death_year":null},{"id":8958,"created_at":"2025-06-06T23:23:50.589Z","updated_at":"2025-06-06T23:23:50.589Z","last_name":"Mcbee","first_name":"Elmer","middle_name":"Wm","sex":"Male","race":"Black","name_prefix":null,"name_suffix":null,"searchable_name":"Elmer Wm Mcbee","birth_year":1898,"is_birth_year_estimated":true,"pob":"Iowa","is_pob_estimated":true,"notes":null,"description":null,"sortable_name":"Mcbee, Elmer, Wm","death_year":null},{"id":8959,"created_at":"2025-06-06T23:23:50.664Z","updated_at":"2025-06-06T23:23:50.664Z","last_name":"Branche","first_name":"Emmett","middle_name":null,"sex":"Male","race":"Black","name_prefix":null,"name_suffix":null,"searchable_name":"Emmett Branche","birth_year":1900,"is_birth_year_estimated":true,"pob":"Ohio","is_pob_estimated":true,"notes":null,"description":null,"sortable_name":"Branche, Emmett, ","death_year":null},{"id":9015,"created_at":"2025-06-06T23:23:54.956Z","updated_at":"2025-06-06T23:23:54.956Z","last_name":"Ford","first_name":"Cyrus","middle_name":null,"sex":"Male","race":"Black","name_prefix":null,"name_suffix":null,"searchable_name":"Cyrus Ford","birth_year":1896,"is_birth_year_estimated":true,"pob":"California","is_pob_estimated":true,"notes":null,"description":null,"sortable_name":"Ford, Cyrus, ","death_year":null},{"id":9370,"created_at":"2025-06-06T23:24:22.056Z","updated_at":"2025-06-06T23:24:22.056Z","last_name":"Stradford","first_name":"John","middle_name":"B","sex":"Male","race":"Black","name_prefix":null,"name_suffix":null,"searchable_name":"John B Stradford","birth_year":1866,"is_birth_year_estimated":true,"pob":"Kentucky","is_pob_estimated":true,"notes":null,"description":null,"sortable_name":"Stradford, John, B","death_year":null},{"id":9373,"created_at":"2025-06-06T23:24:22.274Z","updated_at":"2025-06-06T23:24:22.274Z","last_name":"Armstead","first_name":"P","middle_name":null,"sex":"Male","race":"Black","name_prefix":null,"name_suffix":null,"searchable_name":"P Armstead","birth_year":1894,"is_birth_year_estimated":true,"pob":"Arkansas","is_pob_estimated":true,"notes":null,"description":null,"sortable_name":"Armstead, P, ","death_year":null},{"id":9377,"created_at":"2025-06-06T23:24:22.566Z","updated_at":"2025-06-06T23:24:22.566Z","last_name":"Stewart","first_name":"John","middle_name":"E","sex":"Male","race":"Black","name_prefix":null,"name_suffix":null,"searchable_name":"John E Stewart","birth_year":1888,"is_birth_year_estimated":true,"pob":"Texas","is_pob_estimated":true,"notes":null,"description":null,"sortable_name":"Stewart, John, E","death_year":null},{"id":9379,"created_at":"2025-06-06T23:24:22.705Z","updated_at":"2025-06-06T23:24:22.705Z","last_name":"James","first_name":"Edward","middle_name":null,"sex":"Male","race":"Black","name_prefix":null,"name_suffix":null,"searchable_name":"Edward James","birth_year":1894,"is_birth_year_estimated":true,"pob":"Alabama","is_pob_estimated":true,"notes":null,"description":null,"sortable_name":"James, Edward, ","death_year":null},{"id":9381,"created_at":"2025-06-06T23:24:22.861Z","updated_at":"2025-06-06T23:24:22.861Z","last_name":"Abbott","first_name":"Harry","middle_name":"O","sex":"Male","race":"Black","name_prefix":null,"name_suffix":null,"searchable_name":"Harry O Abbott","birth_year":1890,"is_birth_year_estimated":true,"pob":"Kansas","is_pob_estimated":true,"notes":null,"description":null,"sortable_name":"Abbott, Harry, O","death_year":null}]}}
]}